helloworldplayerlili/__init__.py
helloworldplayerlili/lala.py
helloworldplayerlili/player.py
helloworldplayerlili-0.0.3.dist-info/LICENSE
helloworldplayerlili-0.0.3.dist-info/METADATA
helloworldplayerlili-0.0.3.dist-info/WHEEL
helloworldplayerlili-0.0.3.dist-info/top_level.txt
helloworldplayerlili-0.0.3.dist-info/RECORD
