Metadata-Version: 2.1
Name: helloworldplayerlili
Version: 0.0.3
License-File: LICENSE
